<?xml version = '1.0' encoding = 'UTF-8'?>
<DataTypesDesign class="oracle.dbtools.crest.model.design.datatypes.DataTypesDesign" name="DataTypes" id="26064990-2988-0A1F-6D01-77A16BBFC758" mainViewID="BC35A0B0-78A1-A82A-C924-E1E1ACE5D400">
<createdBy>Willywes</createdBy>
<createdTime>2017-04-15 05:52:15 UTC</createdTime>
<generatorID>Generado por el Usuario</generatorID>
<ownerDesignName>modeloRemasterizado</ownerDesignName>
<shouldBeOpen>false</shouldBeOpen>
<collectionOfRefsPrefix>array_ref_</collectionOfRefsPrefix>
<collectionPrefix>array_</collectionPrefix>
<defaultArrayLimit>10</defaultArrayLimit>
<defaultCollectionType_Kind>ARRAY</defaultCollectionType_Kind>
<defaultCollectionType_Suffix>_Array</defaultCollectionType_Suffix>
<embeddedStructuredTypePrefix>inst_</embeddedStructuredTypePrefix>
<referencePrefix>ref_</referencePrefix>
<useRoleInAssociationEndAsName>true</useRoleInAssociationEndAsName>
</DataTypesDesign>